gee_asset_manager/__init__.py
gee_asset_manager/batch_copy.py
gee_asset_manager/batch_info.py
gee_asset_manager/batch_remover.py
gee_asset_manager/batch_uploader.py
gee_asset_manager/config.py
gee_asset_manager/logconfig.json
gee_asset_manager/metadata_loader.py
gee_asset_manager/session.py
geebam-0.1.7.dist-info/LICENSE
geebam-0.1.7.dist-info/METADATA
geebam-0.1.7.dist-info/WHEEL
geebam-0.1.7.dist-info/entry_points.txt
geebam-0.1.7.dist-info/top_level.txt
geebam-0.1.7.dist-info/RECORD
